.gitignore
CHANGES.txt
LICENSE
MANIFEST.in
README.rst
setup.py
django_giza.egg-info/PKG-INFO
django_giza.egg-info/SOURCES.txt
django_giza.egg-info/dependency_links.txt
django_giza.egg-info/top_level.txt
giza/__init__.py
giza/management/__init__.py
giza/management/commands/__init__.py
giza/management/commands/giza.py