Metadata-Version: 1.1
Name: django-giza
Version: 0.1.2
Summary: Autodoc all modules from a Django project's INSTALLED_APPS for Sphinx
Home-page: https://github.com/anentropic/giza
Author: Anentropic
Author-email: ego@anentropic.com
License: LICENSE.txt
Platform: UNKNOWN
Classifier: Development Status :: 3 - Alpha
Classifier: License :: OSI Approved :: BSD License
Classifier: Framework :: Django
Classifier: Environment :: Web Environment
Classifier: Intended Audience :: Developers
Classifier: Intended Audience :: System Administrators
Classifier: Operating System :: OS Independent
Classifier: Topic :: Software Development :: Libraries :: Python Modules
Classifier: Programming Language :: Python
